jsonurl_py.py
jsonurl_py-0.4.0.dist-info/entry_points.txt
jsonurl_py-0.4.0.dist-info/LICENSE
jsonurl_py-0.4.0.dist-info/WHEEL
jsonurl_py-0.4.0.dist-info/METADATA
jsonurl_py-0.4.0.dist-info/RECORD
