Metadata-Version: 2.1
Name: jsonurl-py
Version: 0.4.0
Summary: Python implementation of jsonurl, an alternative format for JSON data model
Author-email: Leonard Crestez <cdleonard@gmail.com>
Requires-Python: >=3.7
Classifier: License :: OSI Approved :: MIT License
Requires-Dist: sphinx ; extra == "docs"
Requires-Dist: sphinx-argparse ; extra == "docs"
Requires-Dist: sphinx-rtd-theme ; extra == "docs"
Requires-Dist: tox ; extra == "hack"
Requires-Dist: black ; extra == "hack"
Requires-Dist: pre-commit ; extra == "hack"
Requires-Dist: flit ; extra == "hack"
Requires-Dist: mypy ; extra == "hack"
Requires-Dist: pytest ; extra == "test"
Requires-Dist: pytest-cov ; extra == "test"
Requires-Dist: pytest-benchmark ; extra == "test"
Requires-Dist: coverage-badge ; extra == "test"
Project-URL: Documentation, https://cdleonard.github.io/jsonurl-py/docs/
Project-URL: Homepage, https://github.com/cdleonard/jsonurl-py
Provides-Extra: docs
Provides-Extra: hack
Provides-Extra: test
